raise_me/__init__.py
raise_me/app.py
raise_me/build/__init__.py
raise_me/build/cloud/__init__.py
raise_me/build/cloud/aws.py
raise_me/build/cloud/builder.py
raise_me/build/cloud/gcp.py
raise_me/build/openwhisk.py
raise_me/exceptions/__init__.py
raise_me/identity/__init__.py
raise_me/identity/openwhisk.py
raise_me/models/__init__.py
raise_me/models/deployment.py
raise_me/models/event/__init__.py
raise_me/models/event/http_method.py
raise_me/models/event/raise_event.py
raise_me/models/event/source.py
raise_me/models/event/target.py
raise_me/parser/__init__.py
raise_me/parser/config.py
raise_me/parser/deployment.py
raise_me/parser/event/__init__.py
raise_me/parser/event/filter_.py
raise_me/parser/event/raise_event.py
raise_me/parser/event/source.py
raise_me/parser/event/target.py
raise_me/parser/yaml_parser.py
raise_me/resources/aws/lambda/functions/openwhisk_trigger.py
raise_me/resources/aws/lambda/functions/openwhisk_trigger.zip
raise_me/resources/aws/lambda/layers/cloudevents-1.6.1.zip
raise_me/resources/aws/lambda/layers/requests-2.28.1.zip
raise_me/resources/gcp/workflows/openwhisk_trigger.yaml
raise_me/util/__init__.py
raise_me/util/gcp/__init__.py
raise_me/util/gcp/workflows.py
raise_me/wsk/__init__.py
raise_me/wsk/client.py
raise_me/wsk/http_invoker.py
raise_me/wsk/http_mediator.py
raise_me-0.0.3.dist-info/entry_points.txt
raise_me-0.0.3.dist-info/LICENSE
raise_me-0.0.3.dist-info/WHEEL
raise_me-0.0.3.dist-info/METADATA
raise_me-0.0.3.dist-info/RECORD
