Metadata-Version: 2.1
Name: raise-me
Version: 0.0.3
Summary: Serverless event broker which allows connecting native cloud events (AWS & GCP) to targets declaratively.
Home-page: https://github.com/ferancona/raise-me
License: MIT
Keywords: serverless,openwhisk,pulumi,aws,gcp
Author: Fernando Ancona
Author-email: f.anconac@gmail.com
Requires-Python: >=3.10,<4.0
Classifier: License :: OSI Approved :: MIT License
Classifier: Programming Language :: Python :: 3
Classifier: Programming Language :: Python :: 3.10
Requires-Dist: boto3 (>=1.24.50,<2.0.0)
Requires-Dist: cloudevents (>=1.6.1,<2.0.0)
Requires-Dist: constructs (>=10.1.85,<11.0.0)
Requires-Dist: pulumi (>=3.38.0,<4.0.0)
Requires-Dist: pulumi-aws (>=5.11.0,<6.0.0)
Requires-Dist: pulumi-gcp (>=6.37.0,<7.0.0)
Requires-Dist: requests (>=2.28.1,<3.0.0)
Requires-Dist: ruamel.yaml (>=0.17.21,<0.18.0)
Requires-Dist: typer[all] (>=0.6.1,<0.7.0)
Project-URL: Repository, https://github.com/ferancona/raise-me
